YingyongGailvTongjiJichuJiSuanfaYujiangsheng/README.md
YingyongGailvTongjiJichuJiSuanfaYujiangsheng/__init__.py
YingyongGailvTongjiJichuJiSuanfaYujiangsheng/__main__.py
YingyongGailvTongjiJichuJiSuanfaYujiangsheng/file.pdf
YingyongGailvTongjiJichuJiSuanfaYujiangsheng/index.html
yingyong_gailv_tongji_jichu_ji_suanfa_yujiangsheng-2024.3.2.0.dist-info/METADATA
yingyong_gailv_tongji_jichu_ji_suanfa_yujiangsheng-2024.3.2.0.dist-info/WHEEL
yingyong_gailv_tongji_jichu_ji_suanfa_yujiangsheng-2024.3.2.0.dist-info/entry_points.txt
yingyong_gailv_tongji_jichu_ji_suanfa_yujiangsheng-2024.3.2.0.dist-info/top_level.txt
yingyong_gailv_tongji_jichu_ji_suanfa_yujiangsheng-2024.3.2.0.dist-info/RECORD
